jao/__init__.py
jao/exceptions.py
jao/jao.py
jao/jao_intraday.py
jao/jao_intraday_ida.py
jao/jao_nordic.py
jao/jao_parrun.py
jao/parsers.py
jao/util.py
jao/webservice.py
jao/CWE/__init__.py
jao/CWE/definitions.py
jao/CWE/exceptions.py
jao/CWE/jao.py
jao/CWE/parsers.py
jao_py-0.6.8.dist-info/licenses/LICENSE.MD
jao_py-0.6.8.dist-info/METADATA
jao_py-0.6.8.dist-info/WHEEL
jao_py-0.6.8.dist-info/top_level.txt
jao_py-0.6.8.dist-info/RECORD
