Metadata-Version: 2.4
Name: jao-py
Version: 0.6.8
Summary: A python API wrapper for JAO.eu
Home-page: https://github.com/fboerman/jao-py
Author: Frank Boerman
Author-email: frank@fboerman.nl
License: MIT
Keywords: JAO data api energy
Classifier: Development Status :: 4 - Beta
Classifier: Intended Audience :: Developers
Classifier: Topic :: Scientific/Engineering
Classifier: License :: OSI Approved :: MIT License
Classifier: Programming Language :: Python :: 3.9
Classifier: Programming Language :: Python :: 3.10
Classifier: Programming Language :: Python :: 3.11
Classifier: Programming Language :: Python :: 3.12
Classifier: Programming Language :: Python :: 3.13
License-File: LICENSE.MD
Requires-Dist: requests
Requires-Dist: pandas
Requires-Dist: python-dateutil
Requires-Dist: beautifulsoup4
Dynamic: author
Dynamic: author-email
Dynamic: classifier
Dynamic: description
Dynamic: description-content-type
Dynamic: home-page
Dynamic: keywords
Dynamic: license
Dynamic: license-file
Dynamic: requires-dist
Dynamic: summary
